rasdapy/__init__.py
rasdapy/db_connector.py
rasdapy/query_executor.py
rasdapy/ras_oqlquery.py
rasdapy/cores/__init__.py
rasdapy/cores/core.py
rasdapy/cores/exception_factories.py
rasdapy/cores/remote_procedures.py
rasdapy/cores/request_factories.py
rasdapy/cores/surface.py
rasdapy/cores/utils.py
rasdapy/models/__init__.py
rasdapy/models/complex.py
rasdapy/models/composite_type.py
rasdapy/models/minterval.py
rasdapy/models/ras_gmrray.py
rasdapy/models/ras_storage_layout.py
rasdapy/models/result_array.py
rasdapy/models/sinterval.py
rasdapy/stubs/__init__.py
rasdapy/stubs/client_rassrvr_service_pb2.py
rasdapy/stubs/common_service_pb2.py
rasdapy/stubs/rasmgr_client_service_pb2.py
rasdapy-1.1.0.dist-info/DESCRIPTION.rst
rasdapy-1.1.0.dist-info/METADATA
rasdapy-1.1.0.dist-info/RECORD
rasdapy-1.1.0.dist-info/WHEEL
rasdapy-1.1.0.dist-info/entry_points.txt
rasdapy-1.1.0.dist-info/metadata.json
rasdapy-1.1.0.dist-info/top_level.txt
