Metadata-Version: 2.0
Name: rasdapy
Version: 1.1.0
Summary: Python interface to rasdaman
Home-page: http://rasdaman.org/browser/applications/rasdapy
Author: Bang Pham Huu
Author-email: b.phamhuu@jacobs-university.de
License: LGPL
Keywords: rasdaman interface python
Platform: UNKNOWN
Classifier: Development Status :: 4 - Beta
Classifier: Intended Audience :: Developers
Classifier: Topic :: Software Development :: Libraries
Classifier: License :: OSI Approved :: GNU Library or Lesser General Public License (LGPL)
Classifier: Programming Language :: Python :: 2.7
Classifier: Programming Language :: Python :: 3.4
Classifier: Programming Language :: Python :: 3.5
Classifier: Programming Language :: Python :: 3.6
Provides-Extra: test
Provides-Extra: dev
Requires-Dist: numpy (>=1.7.1)
Requires-Dist: grpcio (>=1.0.0)
Requires-Dist: protobuf (>=3.0.0)
Provides-Extra: dev
Requires-Dist: check-manifest; extra == 'dev'
Provides-Extra: test
Requires-Dist: coverage; extra == 'test'
